CHANGES.txt
LICENSE.txt
MANIFEST.in
README.txt
setup.py
js/__init__.py
js.ckeditor.egg-info/PKG-INFO
js.ckeditor.egg-info/SOURCES.txt
js.ckeditor.egg-info/dependency_links.txt
js.ckeditor.egg-info/entry_points.txt
js.ckeditor.egg-info/namespace_packages.txt
js.ckeditor.egg-info/not-zip-safe
js.ckeditor.egg-info/requires.txt
js.ckeditor.egg-info/top_level.txt
js/ckeditor/__init__.py
js/ckeditor/test_ckeditor.txt
js/ckeditor/resources/ckeditor.js
js/ckeditor/resources/ckeditor_basic.js
js/ckeditor/resources/ckeditor_basic_source.js
js/ckeditor/resources/ckeditor_source.js
js/ckeditor/resources/config.js
js/ckeditor/resources/contents.css
js/ckeditor/resources/_source/adapters/jquery.js
js/ckeditor/resources/_source/core/_bootstrap.js
js/ckeditor/resources/_source/core/ckeditor.js
js/ckeditor/resources/_source/core/ckeditor_base.js
js/ckeditor/resources/_source/core/ckeditor_basic.js
js/ckeditor/resources/_source/core/command.js
js/ckeditor/resources/_source/core/commanddefinition.js
js/ckeditor/resources/_source/core/config.js
js/ckeditor/resources/_source/core/dataprocessor.js
js/ckeditor/resources/_source/core/dom.js
js/ckeditor/resources/_source/core/dtd.js
js/ckeditor/resources/_source/core/editor.js
js/ckeditor/resources/_source/core/editor_basic.js
js/ckeditor/resources/_source/core/env.js
js/ckeditor/resources/_source/core/event.js
js/ckeditor/resources/_source/core/eventInfo.js
js/ckeditor/resources/_source/core/focusmanager.js
js/ckeditor/resources/_source/core/htmlparser.js
js/ckeditor/resources/_source/core/lang.js
js/ckeditor/resources/_source/core/loader.js
js/ckeditor/resources/_source/core/plugindefinition.js
js/ckeditor/resources/_source/core/plugins.js
js/ckeditor/resources/_source/core/resourcemanager.js
js/ckeditor/resources/_source/core/scriptloader.js
js/ckeditor/resources/_source/core/skins.js
js/ckeditor/resources/_source/core/themes.js
js/ckeditor/resources/_source/core/tools.js
js/ckeditor/resources/_source/core/ui.js
js/ckeditor/resources/_source/core/dom/comment.js
js/ckeditor/resources/_source/core/dom/document.js
js/ckeditor/resources/_source/core/dom/documentfragment.js
js/ckeditor/resources/_source/core/dom/domobject.js
js/ckeditor/resources/_source/core/dom/element.js
