Metadata-Version: 1.0
Name: js.ckeditor
Version: 3.6.6
Summary: Fanstatic packaging of CKEditor
Home-page: UNKNOWN
Author: Fanstatic Developers
Author-email: fanstatic@googlegroups.com
License: BSD
Platform: UNKNOWN
